server/__init__.py
server/application.py
server/component/__init__.py
server/component/get_table_info.py
server/component/token_manager.py
mcp_for_odps-0.1.3.dist-info/METADATA
mcp_for_odps-0.1.3.dist-info/WHEEL
mcp_for_odps-0.1.3.dist-info/entry_points.txt
mcp_for_odps-0.1.3.dist-info/licenses/LICENSE
mcp_for_odps-0.1.3.dist-info/RECORD
