Metadata-Version: 2.4
Name: mcp-for-odps
Version: 0.1.3
Summary: MaxCompute (ODPS) MCP Server for getting table information and DDL
Project-URL: Homepage, https://github.com/TracyRay-cxr/mcp_for_odps
Project-URL: Repository, https://github.com/TracyRay-cxr/mcp_for_odps
Project-URL: Documentation, https://github.com/TracyRay-cxr/mcp_for_odps#readme
Project-URL: Issues, https://github.com/TracyRay-cxr/mcp_for_odps/issues
Author-email: tracy_ray <846206245@qq.com>
Maintainer-email: bigjunhong <chenjunhong0301@outlook.com>
License: MIT
License-File: LICENSE
Keywords: aliyun,data,maxcompute,mcp,odps
Classifier: Development Status :: 4 - Beta
Classifier: Intended Audience :: Developers
Classifier: License :: OSI Approved :: MIT License
Classifier: Programming Language :: Python :: 3
Classifier: Programming Language :: Python :: 3.13
Classifier: Topic :: Database
Classifier: Topic :: Software Development :: Libraries :: Python Modules
Requires-Python: >=3.13
Requires-Dist: httpx>=0.28.1
Requires-Dist: mcp[cli]>=1.10.1
